{"coord":{"lon":103.8198,"lat":1.3521},"weather":[{"id":802,"main":"Clouds","description":"scattered clouds","icon":"03d"}],"base":"stations","main":{"temp":29.18,"feels_like":33.93,"temp_min":28.67,"temp_max":30.92,"pressure":1008,"humidity":74,"sea_level":1008,"grnd_level":1007},"visibility":10000,"wind":{"speed":4.63,"deg":40},"clouds":{"all":40},"dt":1760419291,"sys":{"type":1,"id":9470,"country":"SG","sunrise":1760395681,"sunset":1760439191},"timezone":28800,"id":1880755,"name":"Bright Hill Crescent","cod":200}