{"coord":{"lon":103.8198,"lat":1.3521},"weather":[{"id":802,"main":"Clouds","description":"scattered clouds","icon":"03d"}],"base":"stations","main":{"temp":30.48,"feels_like":37.48,"temp_min":30.24,"temp_max":31.44,"pressure":1010,"humidity":77,"sea_level":1010,"grnd_level":1009},"visibility":10000,"wind":{"speed":1.39,"deg":164,"gust":1.42},"clouds":{"all":47},"dt":1747534922,"sys":{"type":2,"id":2100385,"country":"SG","sunrise":1747522549,"sunset":1747566402},"timezone":28800,"id":1880755,"name":"Bright Hill Crescent","cod":200}