{"coord":{"lon":103.82,"lat":1.35},"weather":[{"id":520,"main":"Rain","description":"light intensity shower rain","icon":"09d"}],"base":"stations","main":{"temp":25.2,"feels_like":26.1,"temp_min":24.73,"temp_max":25.75,"pressure":1011,"humidity":89,"sea_level":1011,"grnd_level":1010},"visibility":7000,"wind":{"speed":4.12,"deg":210},"rain":{"1h":0.37},"clouds":{"all":40},"dt":1724729446,"sys":{"type":1,"id":9479,"country":"SG","sunrise":1724713328,"sunset":1724757047},"timezone":28800,"id":1880755,"name":"Bright Hill Crescent","cod":200}