{"coord":{"lon":103.82,"lat":1.35},"weather":[{"id":803,"main":"Clouds","description":"broken clouds","icon":"04n"}],"base":"stations","main":{"temp":26.85,"feels_like":29.67,"temp_min":26.7,"temp_max":27.52,"pressure":1010,"humidity":83,"sea_level":1010,"grnd_level":1009},"visibility":10000,"wind":{"speed":2.57,"deg":340},"clouds":{"all":75},"dt":1765467730,"sys":{"type":1,"id":9479,"country":"SG","sunrise":1765407401,"sunset":1765450759},"timezone":28800,"id":1880755,"name":"Bright Hill Crescent","cod":200}