{"coord":{"lon":103.8198,"lat":1.3521},"weather":[{"id":803,"main":"Clouds","description":"broken clouds","icon":"04d"}],"base":"stations","main":{"temp":31.82,"feels_like":34.76,"temp_min":30.77,"temp_max":32.57,"pressure":1008,"humidity":53,"sea_level":1008,"grnd_level":1007},"visibility":10000,"wind":{"speed":6.69,"deg":160},"clouds":{"all":75},"dt":1720686482,"sys":{"type":1,"id":9479,"country":"SG","sunrise":1720652654,"sunset":1720696548},"timezone":28800,"id":1880755,"name":"Bright Hill Crescent","cod":200}