{"coord":{"lon":103.82,"lat":1.35},"weather":[{"id":803,"main":"Clouds","description":"broken clouds","icon":"04n"}],"base":"stations","main":{"temp":29.18,"feels_like":35.71,"temp_min":29.18,"temp_max":29.18,"pressure":1010,"humidity":82,"sea_level":1010,"grnd_level":1009},"visibility":10000,"wind":{"speed":1.35,"deg":139,"gust":1.84},"clouds":{"all":52},"dt":1783460604,"sys":{"type":2,"id":2100477,"country":"SG","sunrise":1783465421,"sunset":1783509321},"timezone":28800,"id":1880755,"name":"Bright Hill Crescent","cod":200}