{"coord":{"lon":103.8198,"lat":1.352},"weather":[{"id":804,"main":"Clouds","description":"overcast clouds","icon":"04n"}],"base":"stations","main":{"temp":29.16,"feels_like":33.28,"temp_min":29.16,"temp_max":29.16,"pressure":1011,"humidity":71,"sea_level":1011,"grnd_level":1011},"visibility":10000,"wind":{"speed":3.41,"deg":112,"gust":4},"clouds":{"all":100},"dt":1759584296,"sys":{"country":"SG","sunrise":1759531829,"sunset":1759575379},"timezone":28800,"id":1880755,"name":"Bright Hill Crescent","cod":200}