{"coord":{"lon":103.82,"lat":1.35},"weather":[{"id":520,"main":"Rain","description":"light intensity shower rain","icon":"09d"}],"base":"stations","main":{"temp":28.58,"feels_like":33.6,"temp_min":28.07,"temp_max":28.75,"pressure":1009,"humidity":80,"sea_level":1009,"grnd_level":1007},"visibility":8000,"wind":{"speed":5.14,"deg":350},"rain":{"1h":0.15},"clouds":{"all":75},"dt":1771399080,"sys":{"type":1,"id":9470,"country":"SG","sunrise":1771370194,"sunset":1771413666},"timezone":28800,"id":1880755,"name":"Bright Hill Crescent","cod":200}