{"coord":{"lon":103.8198,"lat":1.3521},"weather":[{"id":500,"main":"Rain","description":"light rain","icon":"10d"}],"base":"stations","main":{"temp":30.27,"feels_like":35.2,"temp_min":29.67,"temp_max":30.7,"pressure":1009,"humidity":68,"sea_level":1009,"grnd_level":1007},"visibility":10000,"wind":{"speed":4.63,"deg":180},"rain":{"1h":0.15},"clouds":{"all":75},"dt":1723353854,"sys":{"type":1,"id":9479,"country":"SG","sunrise":1723331105,"sunset":1723374895},"timezone":28800,"id":1880755,"name":"Bright Hill Crescent","cod":200}