{"coord":{"lon":103.8198,"lat":1.3521},"weather":[{"id":803,"main":"Clouds","description":"broken clouds","icon":"04d"}],"base":"stations","main":{"temp":29.25,"feels_like":33.48,"temp_min":28.67,"temp_max":29.7,"pressure":1007,"humidity":71,"sea_level":1007,"grnd_level":1006},"visibility":10000,"wind":{"speed":2.57,"deg":220},"clouds":{"all":75},"dt":1765445829,"sys":{"type":1,"id":9479,"country":"SG","sunrise":1765407401,"sunset":1765450758},"timezone":28800,"id":1880755,"name":"Bright Hill Crescent","cod":200}