{"coord":{"lon":103.8198,"lat":1.352},"weather":[{"id":803,"main":"Clouds","description":"broken clouds","icon":"04n"}],"base":"stations","main":{"temp":28.63,"feels_like":31.3,"temp_min":27.7,"temp_max":29.75,"pressure":1007,"humidity":66,"sea_level":1007,"grnd_level":1006},"visibility":10000,"wind":{"speed":6.17,"deg":20},"clouds":{"all":75},"dt":1774612094,"sys":{"type":1,"id":9479,"country":"SG","sunrise":1774566394,"sunset":1774610021},"timezone":28800,"id":1880755,"name":"Bright Hill Crescent","cod":200}