{"coord":{"lon":103.8198,"lat":1.352},"weather":[{"id":804,"main":"Clouds","description":"overcast clouds","icon":"04n"}],"base":"stations","main":{"temp":27.75,"feels_like":32.05,"temp_min":27.75,"temp_max":27.75,"pressure":1009,"humidity":84,"sea_level":1009,"grnd_level":1008},"visibility":10000,"wind":{"speed":0.46,"deg":60,"gust":0.58},"clouds":{"all":100},"dt":1776274034,"sys":{"country":"SG","sunrise":1776294005,"sunset":1776337724},"timezone":28800,"id":1880755,"name":"Bright Hill Crescent","cod":200}