{"coord":{"lon":103.8198,"lat":1.3521},"weather":[{"id":200,"main":"Thunderstorm","description":"thunderstorm with light rain","icon":"11n"},{"id":500,"main":"Rain","description":"light rain","icon":"10n"}],"base":"stations","main":{"temp":26.28,"feels_like":26.28,"temp_min":25.72,"temp_max":26.7,"pressure":1007,"humidity":94,"sea_level":1007,"grnd_level":1005},"visibility":5000,"wind":{"speed":2.57,"deg":30},"rain":{"1h":0.35},"clouds":{"all":75},"dt":1744975025,"sys":{"type":1,"id":9479,"country":"SG","sunrise":1744930769,"sunset":1744974498},"timezone":28800,"id":1880755,"name":"Bright Hill Crescent","cod":200}