{"coord":{"lon":103.82,"lat":1.35},"weather":[{"id":803,"main":"Clouds","description":"broken clouds","icon":"04d"}],"base":"stations","main":{"temp":26.77,"feels_like":29,"temp_min":25.7,"temp_max":26.96,"pressure":1008,"humidity":77,"sea_level":1008,"grnd_level":1007},"visibility":10000,"wind":{"speed":3.6,"deg":180},"clouds":{"all":75},"dt":1756802471,"sys":{"type":1,"id":9479,"country":"SG","sunrise":1756767636,"sunset":1756811329},"timezone":28800,"id":1880755,"name":"Bright Hill Crescent","cod":200}