{"coord":{"lon":103.8198,"lat":1.352},"weather":[{"id":803,"main":"Clouds","description":"broken clouds","icon":"04d"}],"base":"stations","main":{"temp":30.92,"feels_like":32.49,"temp_min":29.18,"temp_max":31.75,"pressure":1007,"humidity":50,"sea_level":1007,"grnd_level":1005},"visibility":10000,"wind":{"speed":5.66,"deg":10},"clouds":{"all":75},"dt":1768721023,"sys":{"type":1,"id":9479,"country":"SG","sunrise":1768691596,"sunset":1768734977},"timezone":28800,"id":1880755,"name":"Bright Hill Crescent","cod":200}