{"coord":{"lon":103.82,"lat":1.35},"weather":[{"id":500,"main":"Rain","description":"light rain","icon":"10d"}],"base":"stations","main":{"temp":31.14,"feels_like":35.4,"temp_min":29.84,"temp_max":31.75,"pressure":1006,"humidity":61,"sea_level":1006,"grnd_level":1005},"visibility":10000,"wind":{"speed":2.57,"deg":250},"rain":{"1h":0.11},"clouds":{"all":75},"dt":1763544976,"sys":{"type":1,"id":9479,"country":"SG","sunrise":1763506116,"sunset":1763549510},"timezone":28800,"id":1880755,"name":"Bright Hill Crescent","cod":200}