{"coord":{"lon":103.8198,"lat":1.352},"weather":[{"id":803,"main":"Clouds","description":"broken clouds","icon":"04n"}],"base":"stations","main":{"temp":28.74,"feels_like":32.52,"temp_min":28.73,"temp_max":29.7,"pressure":1011,"humidity":72,"sea_level":1011,"grnd_level":1009},"visibility":10000,"wind":{"speed":3.6,"deg":100},"clouds":{"all":75},"dt":1729517276,"sys":{"type":1,"id":9479,"country":"SG","sunrise":1729464409,"sunset":1729507892},"timezone":28800,"id":1880755,"name":"Bright Hill Crescent","cod":200}