{"coord":{"lon":103.8198,"lat":1.3521},"weather":[{"id":200,"main":"Thunderstorm","description":"thunderstorm with light rain","icon":"11d"},{"id":501,"main":"Rain","description":"moderate rain","icon":"10d"}],"base":"stations","main":{"temp":26.01,"feels_like":26.01,"temp_min":23.7,"temp_max":30.45,"pressure":1014,"humidity":86},"visibility":7000,"wind":{"speed":2.57,"deg":110},"rain":{"1h":2.73},"clouds":{"all":75},"dt":1691036769,"sys":{"type":1,"id":9479,"country":"SG","sunrise":1691017542,"sunset":1691061367},"timezone":28800,"id":1880755,"name":"Bright Hill Crescent","cod":200}