{"coord":{"lon":103.82,"lat":1.35},"weather":[{"id":520,"main":"Rain","description":"light intensity shower rain","icon":"09d"}],"base":"stations","main":{"temp":24.78,"feels_like":25.77,"temp_min":24.7,"temp_max":25.36,"pressure":1008,"humidity":94},"visibility":8000,"wind":{"speed":1.54,"deg":0},"rain":{"1h":0.36},"clouds":{"all":75},"dt":1674343581,"sys":{"type":2,"id":265582,"country":"SG","sunrise":1674342861,"sunset":1674386251},"timezone":28800,"id":1880755,"name":"Bright Hill Crescent","cod":200}