{"coord":{"lon":103.8198,"lat":1.3521},"weather":[{"id":803,"main":"Clouds","description":"broken clouds","icon":"04n"}],"base":"stations","main":{"temp":29.6,"feels_like":33.24,"temp_min":28.57,"temp_max":30.82,"pressure":1009,"humidity":66,"sea_level":1009,"grnd_level":1008},"visibility":10000,"wind":{"speed":4.12,"deg":140},"clouds":{"all":75},"dt":1750851000,"sys":{"type":1,"id":9479,"country":"SG","sunrise":1750806077,"sunset":1750849992},"timezone":28800,"id":1880755,"name":"Bright Hill Crescent","cod":200}